LICENSE
MANIFEST.in
README.rst
setup.cfg
setup.py
django_blogposts/__init__.py
django_blogposts/admin.py
django_blogposts/sitemap.py
django_blogposts/urls.py
django_blogposts/views.py
django_blogposts.egg-info/PKG-INFO
django_blogposts.egg-info/SOURCES.txt
django_blogposts.egg-info/dependency_links.txt
django_blogposts.egg-info/requires.txt
django_blogposts.egg-info/top_level.txt
django_blogposts/__pycache__/__init__.cpython-34.pyc
django_blogposts/__pycache__/admin.cpython-34.pyc
django_blogposts/__pycache__/urls.cpython-34.pyc
django_blogposts/__pycache__/views.cpython-34.pyc
django_blogposts/locale/ru/LC_MESSAGES/django.mo
django_blogposts/locale/ru/LC_MESSAGES/django.po
django_blogposts/migrations/0001_initial.py
django_blogposts/migrations/0002_auto_20160205_0923.py
django_blogposts/migrations/0003_auto_20160210_0934.py
django_blogposts/migrations/0004_categories.py
django_blogposts/migrations/0005_blogpost_category.py
django_blogposts/migrations/0006_auto_20160301_0905.py
django_blogposts/migrations/0007_auto_20160301_1014.py
django_blogposts/migrations/0008_auto_20160301_1015.py
django_blogposts/migrations/0009_auto_20160404_1115.py
django_blogposts/migrations/0010_auto_20180806_2103.py
django_blogposts/migrations/__init__.py
django_blogposts/migrations/__pycache__/0001_initial.cpython-34.pyc
django_blogposts/migrations/__pycache__/0002_auto_20160205_0923.cpython-34.pyc
django_blogposts/migrations/__pycache__/0003_auto_20160210_0934.cpython-34.pyc
django_blogposts/migrations/__pycache__/0004_categories.cpython-34.pyc
django_blogposts/migrations/__pycache__/0005_blogpost_category.cpython-34.pyc
django_blogposts/migrations/__pycache__/0006_auto_20160301_0905.cpython-34.pyc
django_blogposts/migrations/__pycache__/0007_auto_20160301_1014.cpython-34.pyc
django_blogposts/migrations/__pycache__/0008_auto_20160301_1015.cpython-34.pyc
django_blogposts/migrations/__pycache__/0009_auto_20160404_1115.cpython-34.pyc
django_blogposts/migrations/__pycache__/0010_auto_20180806_2103.cpython-34.pyc
django_blogposts/migrations/__pycache__/__init__.cpython-34.pyc
django_blogposts/models/__init__.py
django_blogposts/models/blogpost.py
django_blogposts/models/categories.py
