Metadata-Version: 1.0
Name: django-blogposts
Version: 0.3.7
Summary: Django module for simple blog
Home-page: UNKNOWN
Author: Spi4ka
Author-email: UNKNOWN
License: UNKNOWN
Platform: UNKNOWN
